aquitania/__init__.py
aquitania/bot.py
aquitania/brains/__init__.py
aquitania/brains/brains_manager.py
aquitania/brains/evaluator.py
aquitania/brains/model_manager.py
aquitania/brains/is_oos_split/__init__.py
aquitania/brains/is_oos_split/abstract_is_oos_split.py
aquitania/brains/is_oos_split/train_test_split.py
aquitania/brains/model_selection/__init__.py
aquitania/brains/model_selection/abstract_model_selection.py
aquitania/brains/model_selection/inverse_kfolder.py
aquitania/brains/model_selection/kfolder.py
aquitania/brains/models/__init__.py
aquitania/brains/models/abstract_model.py
aquitania/brains/models/extra_trees.py
aquitania/brains/models/random_forest.py
aquitania/brains/statistics/__init__.py
aquitania/brains/statistics/categories.py
aquitania/brains/statistics/util.py
aquitania/data_processing/__init__.py
aquitania/data_processing/analytics_loader.py
aquitania/data_processing/indicator_pipeline.py
aquitania/data_processing/indicator_transformer.py
aquitania/data_processing/util.py
aquitania/data_source/__init__.py
aquitania/data_source/feeder.py
aquitania/data_source/historic_data_manager.py
aquitania/data_source/ninjatrader.py
aquitania/data_source/broker/__init__.py
aquitania/data_source/broker/abstract_data_source.py
aquitania/data_source/broker/broker_selection.py
aquitania/data_source/broker/fxcm.py
aquitania/data_source/broker/oanda.py
aquitania/data_source/broker/test_broker.py
aquitania/data_source/storage/__init__.py
aquitania/data_source/storage/abstract_storage_system.py
aquitania/data_source/storage/pandas_h5.py
aquitania/data_source/storage/sanity_check.py
aquitania/execution/__init__.py
aquitania/execution/kelly.py
aquitania/execution/margin_manager.py
aquitania/execution/monte_carlo.py
aquitania/execution/oracle.py
aquitania/execution/oracle_criteria.py
aquitania/execution/oracle_manager.py
aquitania/execution/order.py
aquitania/execution/order_manager.py
aquitania/execution/order_size.py
aquitania-0.0.4.12.dist-info/DESCRIPTION.rst
aquitania-0.0.4.12.dist-info/METADATA
aquitania-0.0.4.12.dist-info/RECORD
aquitania-0.0.4.12.dist-info/WHEEL
aquitania-0.0.4.12.dist-info/metadata.json
aquitania-0.0.4.12.dist-info/top_level.txt
